{
  "id": "ex_casual_53980273",
  "intent": "Clean up the tagmented samples on the magnetic module by pulling off the old supernatant, then add the PCR master mix and index adapters to each sample before putting them on the thermal cycler",
  "config": {
    "labware": {
      "tag1_plate": {
        "load_name": "agilentwithnonskirted_96_wellplate_200ul",
        "slot": "TAG1 plate"
      },
      "index adapter plate": {
        "load_name": "agilent_96_wellplate_200ul",
        "slot": "5"
      },
      "reagent_plate": {
        "load_name": "quantgene_96_aluminumblock_200ul",
        "slot": "reagent plate"
      },
      "reagent reservoir": {
        "load_name": "nest_12_reservoir_15ml",
        "slot": "8"
      }
    },
    "pipettes": {
      "right": {
        "model": "p20_multi_gen2",
        "tipracks": []
      },
      "left": {
        "model": "p300_multi_gen2",
        "tipracks": []
      }
    },
    "modules": {
      "tempdeck": {
        "module_type": "temperature",
        "slot": "4"
      },
      "magdeck": {
        "module_type": "magnetic",
        "slot": "7"
      }
    }
  },
  "style": "casual",
  "source_file": "amplify2.ot2.apiv2.py",
  "output_schema": {
    "protocol_name": "6. Illumina COVIDSeq - Amplify Tagmented Amplicons",
    "author": "Opentrons <protocols@opentrons.com>",
    "labware": [
      {
        "slot": "TAG1 plate",
        "load_name": "agilentwithnonskirted_96_wellplate_200ul",
        "label": "tag1_plate"
      },
      {
        "slot": "5",
        "load_name": "agilent_96_wellplate_200ul",
        "label": "index adapter plate"
      },
      {
        "slot": "reagent plate",
        "load_name": "quantgene_96_aluminumblock_200ul",
        "label": "reagent_plate"
      },
      {
        "slot": "8",
        "load_name": "nest_12_reservoir_15ml",
        "label": "reagent reservoir"
      }
    ],
    "pipettes": [
      {
        "mount": "right",
        "model": "p20_multi_gen2",
        "tipracks": []
      },
      {
        "mount": "left",
        "model": "p300_multi_gen2",
        "tipracks": []
      }
    ],
    "modules": [
      {
        "module_type": "temperature",
        "slot": "4",
        "label": "tempdeck"
      },
      {
        "module_type": "magnetic",
        "slot": "7",
        "label": "magdeck"
      }
    ],
    "commands": [
      {
        "command_type": "set_temperature",
        "module": "tempdeck",
        "celsius": 4
      },
      {
        "command_type": "disengage_magnets",
        "module": "magdeck"
      },
      {
        "command_type": "pick_up_tip",
        "pipette": "left"
      },
      {
        "command_type": "pick_up_tip",
        "pipette": "left"
      },
      {
        "command_type": "pause",
        "pipette": "left",
        "message": "\n\n\n\nReplace 200ul filtertipracks before resuming.\n\n\n\n"
      },
      {
        "command_type": "pick_up_tip",
        "pipette": "left"
      },
      {
        "command_type": "aspirate",
        "pipette": "left",
        "volume": "vol"
      },
      {
        "command_type": "dispense",
        "pipette": "left",
        "volume": "vol",
        "labware": "liquid_trash",
        "well": "A1"
      },
      {
        "command_type": "return_tip",
        "pipette": "left"
      },
      {
        "command_type": "drop_tip",
        "pipette": "left"
      },
      {
        "command_type": "aspirate",
        "pipette": "left",
        "volume": "vol"
      },
      {
        "command_type": "dispense",
        "pipette": "left",
        "volume": "vol"
      },
      {
        "command_type": "aspirate",
        "pipette": "left",
        "volume": 200
      },
      {
        "command_type": "dispense",
        "pipette": "left",
        "volume": 200
      },
      {
        "command_type": "aspirate",
        "pipette": "left",
        "volume": "vol_per_transfer"
      },
      {
        "command_type": "dispense",
        "pipette": "left",
        "volume": "vol_per_transfer"
      },
      {
        "command_type": "mix",
        "pipette": "left",
        "repetitions": "mixreps",
        "volume": "vol_mix"
      },
      {
        "command_type": "air_gap",
        "pipette": "left",
        "volume": 20
      },
      {
        "command_type": "return_tip",
        "pipette": "left"
      },
      {
        "command_type": "drop_tip",
        "pipette": "left"
      },
      {
        "command_type": "delay",
        "pipette": "left",
        "minutes": "time_incubation"
      },
      {
        "command_type": "engage_magnets",
        "module": "magdeck",
        "height": "engage_height"
      },
      {
        "command_type": "delay",
        "pipette": "left",
        "minutes": "time_settling"
      },
      {
        "command_type": "disengage_magnets",
        "module": "magdeck"
      },
      {
        "command_type": "engage_magnets",
        "module": "magdeck",
        "height": "engage_height"
      },
      {
        "command_type": "delay",
        "pipette": "left",
        "minutes": "time_settling_minutes"
      },
      {
        "command_type": "aspirate",
        "pipette": "left",
        "volume": "vol_mm"
      },
      {
        "command_type": "dispense",
        "pipette": "left",
        "volume": "vol_mm"
      },
      {
        "command_type": "return_tip",
        "pipette": "left"
      },
      {
        "command_type": "drop_tip",
        "pipette": "left"
      },
      {
        "command_type": "aspirate",
        "pipette": "right",
        "volume": "vol_index_adapter"
      },
      {
        "command_type": "dispense",
        "pipette": "right",
        "volume": "vol_index_adapter"
      },
      {
        "command_type": "return_tip",
        "pipette": "right"
      },
      {
        "command_type": "drop_tip",
        "pipette": "right"
      },
      {
        "command_type": "comment",
        "pipette": "left",
        "message": "\n\n\n\nSeal and shake at 1600 rpm for 1 minute. If liquid is visible on the seal, centrifuge at 500 x g for 1 minute. Inspect to make sure beads are resuspended. To resuspend, set your pipette to 35 \u00b5l with the plunger down, and then slowly pipette to mix. Place on the preprogrammed thermal cycler and run the COVIDSeq TAG PCR program"
      }
    ]
  }
}