{
  "id": "ex_casual_270e417e",
  "intent": "Run the full QuantSeq library prep workflow - start with RNA samples, do RT reactions with barcoded primers, pool them together, clean up with magnetic beads and ethanol washes a bunch of times, remove the RNA, do some PCR optimization to figure out how many cycles to run, then do the final PCR and more cleanup steps to get sequencing-ready libraries",
  "config": {
    "labware": {
      "Tube Rack for Reagents": {
        "load_name": "opentrons_24_tuberack_nest_1.5ml_snapcap",
        "slot": "2"
      },
      "mag_plate": {
        "load_name": "nest_96_wellplate_2ml_deep",
        "slot": "Magnetic Module Plate"
      },
      "Nest 100 uL PCR plate in slot 5": {
        "load_name": "nest_96_wellplate_100ul_pcr_full_skirt",
        "slot": "5"
      },
      "Final Output plate in slot 1": {
        "load_name": "nest_96_wellplate_100ul_pcr_full_skirt",
        "slot": "1"
      },
      "block": {
        "load_name": "opentrons_24_aluminumblock_nest_1.5ml_snapcap",
        "slot": "7"
      },
      "Index Plate": {
        "load_name": "index_96_aluminumblock_200ul",
        "slot": "8"
      }
    },
    "pipettes": {
      "left": {
        "model": "p20_single_gen2",
        "tipracks": []
      },
      "right": {
        "model": "p300_single_gen2",
        "tipracks": []
      }
    },
    "modules": {
      "mag": {
        "module_type": "magnetic",
        "slot": "4"
      },
      "temp": {
        "module_type": "Temperature Module",
        "slot": "7"
      }
    }
  },
  "style": "casual",
  "source_file": "1af856.ot2.apiv2.py",
  "output_schema": {
    "protocol_name": "1af856.ot2.apiv2",
    "author": "Steve Plonk <protocols@opentrons.com>",
    "labware": [
      {
        "slot": "2",
        "load_name": "opentrons_24_tuberack_nest_1.5ml_snapcap",
        "label": "Tube Rack for Reagents"
      },
      {
        "slot": "Magnetic Module Plate",
        "load_name": "nest_96_wellplate_2ml_deep",
        "label": "mag_plate"
      },
      {
        "slot": "5",
        "load_name": "nest_96_wellplate_100ul_pcr_full_skirt",
        "label": "Nest 100 uL PCR plate in slot 5"
      },
      {
        "slot": "1",
        "load_name": "nest_96_wellplate_100ul_pcr_full_skirt",
        "label": "Final Output plate in slot 1"
      },
      {
        "slot": "7",
        "load_name": "opentrons_24_aluminumblock_nest_1.5ml_snapcap",
        "label": "block"
      },
      {
        "slot": "8",
        "load_name": "index_96_aluminumblock_200ul",
        "label": "Index Plate"
      }
    ],
    "pipettes": [
      {
        "mount": "left",
        "model": "p20_single_gen2",
        "tipracks": []
      },
      {
        "mount": "right",
        "model": "p300_single_gen2",
        "tipracks": []
      }
    ],
    "modules": [
      {
        "module_type": "magnetic",
        "slot": "4",
        "label": "mag"
      },
      {
        "module_type": "Temperature Module",
        "slot": "7",
        "label": "temp"
      }
    ],
    "commands": [
      {
        "command_type": "disengage_magnets",
        "module": "mag"
      },
      {
        "command_type": "set_temperature",
        "module": "temp",
        "celsius": 4
      },
      {
        "command_type": "comment",
        "pipette": "left",
        "message": "Ensure reagents in sufficient volume are present on deck."
      },
      {
        "command_type": "comment",
        "pipette": "left",
        "message": "format"
      },
      {
        "command_type": "comment",
        "pipette": "left",
        "message": "\nSTEP - please confirm and resume\n"
      },
      {
        "command_type": "pause",
        "pipette": "left",
        "message": "format"
      },
      {
        "command_type": "comment",
        "pipette": "left",
        "message": "\nSTEP - assemble mastermix\n"
      },
      {
        "command_type": "transfer",
        "pipette": "left",
        "volume": "v",
        "source_labware": "",
        "source_well": "A1",
        "dest_labware": "",
        "dest_well": "A1",
        "new_tip": "always"
      },
      {
        "command_type": "pick_up_tip",
        "pipette": "right"
      },
      {
        "command_type": "mix",
        "pipette": "right",
        "repetitions": 5,
        "volume": "mx_vol"
      },
      {
        "command_type": "drop_tip",
        "pipette": "right"
      },
      {
        "command_type": "comment",
        "pipette": "left",
        "message": "\nSTEP - add 3 uL mastermix to each RT reaction\n"
      },
      {
        "command_type": "transfer",
        "pipette": "left",
        "volume": 3,
        "source_labware": "",
        "source_well": "A1",
        "dest_labware": "",
        "dest_well": "A1",
        "new_tip": "always"
      },
      {
        "command_type": "pause",
        "pipette": "left",
        "message": "\n\nSeal the plate\n\n\nGently vortex to mix\n\n\nSpin\n\n\nIncubate 42 degrees C 15 min\n\n\nSpin\n\n\nReturn plate to slot 8. Resume\n\n\n\n"
      },
      {
        "command_type": "comment",
        "pipette": "left",
        "message": "\nSTEP - combine 9 uL each of up to 56 RT reactions\n"
      },
      {
        "command_type": "pick_up_tip",
        "pipette": "left"
      },
      {
        "command_type": "transfer",
        "pipette": "left",
        "volume": 9,
        "source_labware": "",
        "source_well": "A1",
        "dest_labware": "",
        "dest_well": "A1",
        "new_tip": "never"
      },
      {
        "command_type": "drop_tip",
        "pipette": "left"
      },
      {
        "command_type": "comment",
        "pipette": "left",
        "message": "\nSTEP - add 24 uL beads to each purification\n"
      },
      {
        "command_type": "pick_up_tip",
        "pipette": "right"
      },
      {
        "command_type": "aspirate",
        "pipette": "right",
        "volume": "vol_premix"
      },
      {
        "command_type": "dispense",
        "pipette": "right",
        "volume": "vol_premix"
      },
      {
        "command_type": "aspirate",
        "pipette": "right",
        "volume": 24
      },
      {
        "command_type": "delay",
        "pipette": "left",
        "seconds": 1
      },
      {
        "command_type": "touch_tip",
        "pipette": "right"
      },
      {
        "command_type": "air_gap",
        "pipette": "right",
        "volume": 15
      },
      {
        "command_type": "dispense",
        "pipette": "right",
        "volume": 24
      },
      {
        "command_type": "blow_out",
        "pipette": "right"
      },
      {
        "command_type": "touch_tip",
        "pipette": "right"
      },
      {
        "command_type": "drop_tip",
        "pipette": "right"
      },
      {
        "command_type": "comment",
        "pipette": "left",
        "message": "\nSTEP - add PS for final vol 22.5 uL per sample and mix\n"
      },
      {
        "command_type": "pick_up_tip",
        "pipette": "right"
      },
      {
        "command_type": "aspirate",
        "pipette": "right",
        "volume": "v"
      },
      {
        "command_type": "dispense",
        "pipette": "right",
        "volume": "v"
      },
      {
        "command_type": "mix",
        "pipette": "right",
        "repetitions": 5,
        "volume": "mx_vol"
      },
      {
        "command_type": "drop_tip",
        "pipette": "right"
      },
      {
        "command_type": "comment",
        "pipette": "left",
        "message": "\nSTEP - incubate 5 min room temp\n"
      },
      {
        "command_type": "delay",
        "pipette": "left",
        "minutes": 5
      },
      {
        "command_type": "comment",
        "pipette": "left",
        "message": "\nSTEP - engage magnets for 10 min\n"
      },
      {
        "command_type": "engage_magnets",
        "module": "mag"
      },
      {
        "command_type": "delay",
        "pipette": "left",
        "minutes": 10
      },
      {
        "command_type": "comment",
        "pipette": "left",
        "message": "STEP - processing purifications"
      },
      {
        "command_type": "comment",
        "pipette": "left",
        "message": "\nSTEP - processing purifications: remove initial sup\n"
      },
      {
        "command_type": "pick_up_tip",
        "pipette": "right"
      },
      {
        "command_type": "air_gap",
        "pipette": "right",
        "volume": 20
      },
      {
        "command_type": "aspirate",
        "pipette": "right",
        "volume": "v"
      },
      {
        "command_type": "air_gap",
        "pipette": "right",
        "volume": 20
      },
      {
        "command_type": "dispense",
        "pipette": "right",
        "volume": null
      },
      {
        "command_type": "delay",
        "pipette": "left",
        "seconds": 1
      },
      {
        "command_type": "blow_out",
        "pipette": "right"
      },
      {
        "command_type": "drop_tip",
        "pipette": "right"
      },
      {
        "command_type": "comment",
        "pipette": "left",
        "message": "\nSTEP - purifications: wash 2x with 80 pct EtOH\n"
      },
      {
        "command_type": "pick_up_tip",
        "pipette": "right"
      },
      {
        "command_type": "comment",
        "pipette": "left",
        "message": "\nSTEP - purifications: add 80 pct ethanol\n"
      },
      {
        "command_type": "dispense",
        "pipette": "right",
        "volume": null
      },
      {
        "command_type": "aspirate",
        "pipette": "right",
        "volume": "v"
      },
      {
        "command_type": "air_gap",
        "pipette": "right",
        "volume": 20
      },
      {
        "command_type": "dispense",
        "pipette": "right",
        "volume": null
      },
      {
        "command_type": "delay",
        "pipette": "left",
        "seconds": 1
      },
      {
        "command_type": "blow_out",
        "pipette": "right"
      },
      {
        "command_type": "air_gap",
        "pipette": "right",
        "volume": 20
      },
      {
        "command_type": "delay",
        "pipette": "left",
        "seconds": 30
      },
      {
        "command_type": "comment",
        "pipette": "left",
        "message": "\nSTEP - purifications: remove and discard EtOH\n"
      },
      {
        "command_type": "dispense",
        "pipette": "right",
        "volume": null
      },
      {
        "command_type": "air_gap",
        "pipette": "right",
        "volume": 20
      },
      {
        "command_type": "aspirate",
        "pipette": "right",
        "volume": "v"
      },
      {
        "command_type": "air_gap",
        "pipette": "right",
        "volume": 20
      },
      {
        "command_type": "dispense",
        "pipette": "right",
        "volume": null
      },
      {
        "command_type": "delay",
        "pipette": "left",
        "seconds": 1
      },
      {
        "command_type": "blow_out",
        "pipette": "right"
      },
      {
        "command_type": "aspirate",
        "pipette": "right",
        "volume": 25
      },
      {
        "command_type": "drop_tip",
        "pipette": "right"
      },
      {
        "command_type": "comment",
        "pipette": "left",
        "message": "\nSTEP - purifications: air dry bead pellet\n"
      },
      {
        "command_type": "delay",
        "pipette": "left",
        "minutes": "time_dry"
      },
      {
        "command_type": "comment",
        "pipette": "left",
        "message": "\nSTEP - purifications: elute purification 1\n"
      },
      {
        "command_type": "disengage_magnets",
        "module": "mag"
      },
      {
        "command_type": "comment",
        "pipette": "left",
        "message": "\nSTEP - purifications: elute purification 2\n"
      },
      {
        "command_type": "transfer",
        "pipette": "left",
        "volume": 12,
        "source_labware": "",
        "source_well": "A1",
        "dest_labware": "",
        "dest_well": "A1",
        "new_tip": "always",
        "mix_after": [
          5,
          9
        ]
      },
      {
        "command_type": "delay",
        "pipette": "left",
        "minutes": 2
      },
      {
        "command_type": "engage_magnets",
        "module": "mag"
      },
      {
        "command_type": "delay",
        "pipette": "left",
        "minutes": "time_engage"
      },
      {
        "command_type": "comment",
        "pipette": "left",
        "message": "\nSTEP - recover final purification eluate\n"
      },
      {
        "command_type": "transfer",
        "pipette": "left",
        "volume": 10.5,
        "source_labware": "",
        "source_well": "A1",
        "dest_labware": "",
        "dest_well": "A1",
        "new_tip": "always"
      },
      {
        "command_type": "comment",
        "pipette": "left",
        "message": "\nSTEP - treat with RNA removal solution\n"
      },
      {
        "command_type": "transfer",
        "pipette": "left",
        "volume": 2,
        "source_labware": "",
        "source_well": "A1",
        "dest_labware": "",
        "dest_well": "A1",
        "new_tip": "always",
        "mix_after": [
          5,
          10
        ]
      },
      {
        "command_type": "pause",
        "pipette": "left",
        "message": "\n\nSeal the plate\n\n\nSpin\n\n\nIncubate 95 degrees C 10 min\n\n\nSpin\n\n\nUnseal and return plate to slot 5. Resume\n\n\n\n"
      },
      {
        "command_type": "comment",
        "pipette": "left",
        "message": "\nSTEP - add Random Priming Mix\n"
      },
      {
        "command_type": "transfer",
        "pipette": "left",
        "volume": 6.5,
        "source_labware": "",
        "source_well": "A1",
        "dest_labware": "",
        "dest_well": "A1",
        "new_tip": "always",
        "mix_after": [
          5,
          15
        ]
      },
      {
        "command_type": "comment",
        "pipette": "left",
        "message": "Ensure reagents in sufficient volume are present on deck."
      },
      {
        "command_type": "comment",
        "pipette": "left",
        "message": "format"
      },
      {
        "command_type": "pause",
        "pipette": "left",
        "message": "\n\nSeal the plate\n\n\nSpin\n\n\nIncubate 98 degrees C 2 min\n\n\nCool to 25 degrees C at reduced 0.5 deg/sec\n\n\nIncubate 25 degrees C 3 min\n\n\nSpin\n\n\nUnseal and return plate to slot 5\n\n\nEnsure E2 in sufficient volume is present on deck\n\n\nResume\n\n\n\n"
      },
      {
        "command_type": "comment",
        "pipette": "left",
        "message": "\nSTEP - add E2\n"
      },
      {
        "command_type": "transfer",
        "pipette": "left",
        "volume": 1,
        "source_labware": "",
        "source_well": "A1",
        "dest_labware": "",
        "dest_well": "A1",
        "new_tip": "always",
        "mix_after": [
          5,
          15
        ]
      },
      {
        "command_type": "pause",
        "pipette": "left",
        "message": "\n\nReturn the E2 to its -20 C storage location\n\n\nSeal the plate\n\n\nSpin\n\n\nIncubate 30 degrees C 30 min\n\n\nSpin\n\n\nUnseal and return plate to slot 5. Resume\n\n\n\n"
      },
      {
        "command_type": "comment",
        "pipette": "left",
        "message": "\nSTEP - transfer pool to mag plate\n"
      },
      {
        "command_type": "transfer",
        "pipette": "left",
        "volume": 20,
        "source_labware": "",
        "source_well": "A1",
        "dest_labware": "",
        "dest_well": "A1",
        "new_tip": "always"
      },
      {
        "command_type": "comment",
        "pipette": "left",
        "message": "\nSTEP - add 7 uL beads, wait, engage magnets, wait\n"
      },
      {
        "command_type": "pick_up_tip",
        "pipette": "right"
      },
      {
        "command_type": "aspirate",
        "pipette": "right",
        "volume": "vol_premix"
      },
      {
        "command_type": "dispense",
        "pipette": "right",
        "volume": "vol_premix"
      },
      {
        "command_type": "drop_tip",
        "pipette": "right"
      },
      {
        "command_type": "transfer",
        "pipette": "left",
        "volume": 7,
        "source_labware": "",
        "source_well": "A1",
        "dest_labware": "",
        "dest_well": "A1",
        "new_tip": "always"
      },
      {
        "command_type": "delay",
        "pipette": "left",
        "minutes": 5
      },
      {
        "command_type": "engage_magnets",
        "module": "mag"
      },
      {
        "command_type": "delay",
        "pipette": "left",
        "minutes": "time_engage"
      },
      {
        "command_type": "comment",
        "pipette": "left",
        "message": "\nSTEP - remove sup\n"
      },
      {
        "command_type": "pick_up_tip",
        "pipette": "right"
      },
      {
        "command_type": "aspirate",
        "pipette": "right",
        "volume": 30
      },
      {
        "command_type": "air_gap",
        "pipette": "right",
        "volume": 20
      },
      {
        "command_type": "drop_tip",
        "pipette": "right"
      },
      {
        "command_type": "comment",
        "pipette": "left",
        "message": "\nSTEP - elute\n"
      },
      {
        "command_type": "disengage_magnets",
        "module": "mag"
      },
      {
        "command_type": "transfer",
        "pipette": "right",
        "volume": 40,
        "source_labware": "",
        "source_well": "A1",
        "dest_labware": "",
        "dest_well": "A1",
        "new_tip": "always",
        "mix_after": [
          5,
          32
        ]
      },
      {
        "command_type": "delay",
        "pipette": "left",
        "minutes": 2
      },
      {
        "command_type": "comment",
        "pipette": "left",
        "message": "\nSTEP - add PS\n"
      },
      {
        "command_type": "transfer",
        "pipette": "right",
        "volume": 52,
        "source_labware": "",
        "source_well": "A1",
        "dest_labware": "",
        "dest_well": "A1",
        "new_tip": "always",
        "mix_after": [
          5,
          74
        ]
      },
      {
        "command_type": "delay",
        "pipette": "left",
        "minutes": 5
      },
      {
        "command_type": "engage_magnets",
        "module": "mag"
      },
      {
        "command_type": "delay",
        "pipette": "left",
        "minutes": "time_engage"
      },
      {
        "command_type": "comment",
        "pipette": "left",
        "message": "\nSTEP - remove sup\n"
      },
      {
        "command_type": "pick_up_tip",
        "pipette": "right"
      },
      {
        "command_type": "aspirate",
        "pipette": "right",
        "volume": 100
      },
      {
        "command_type": "air_gap",
        "pipette": "right",
        "volume": 20
      },
      {
        "command_type": "drop_tip",
        "pipette": "right"
      },
      {
        "command_type": "comment",
        "pipette": "left",
        "message": "\nSTEP - add 80 percent EtOH\n"
      },
      {
        "command_type": "pick_up_tip",
        "pipette": "right"
      },
      {
        "command_type": "aspirate",
        "pipette": "right",
        "volume": 120
      },
      {
        "command_type": "air_gap",
        "pipette": "right",
        "volume": 20
      },
      {
        "command_type": "dispense",
        "pipette": "right",
        "volume": 140
      },
      {
        "command_type": "delay",
        "pipette": "left",
        "seconds": 1
      },
      {
        "command_type": "blow_out",
        "pipette": "right"
      },
      {
        "command_type": "delay",
        "pipette": "left",
        "seconds": 30
      },
      {
        "command_type": "comment",
        "pipette": "left",
        "message": "\nSTEP - remove sup\n"
      },
      {
        "command_type": "air_gap",
        "pipette": "right",
        "volume": 20
      },
      {
        "command_type": "aspirate",
        "pipette": "right",
        "volume": 100
      },
      {
        "command_type": "aspirate",
        "pipette": "right",
        "volume": 60
      },
      {
        "command_type": "air_gap",
        "pipette": "right",
        "volume": 20
      },
      {
        "command_type": "drop_tip",
        "pipette": "right"
      },
      {
        "command_type": "dispense",
        "pipette": "right",
        "volume": 200
      },
      {
        "command_type": "delay",
        "pipette": "left",
        "seconds": 1
      },
      {
        "command_type": "blow_out",
        "pipette": "right"
      },
      {
        "command_type": "aspirate",
        "pipette": "right",
        "volume": 25
      },
      {
        "command_type": "drop_tip",
        "pipette": "right"
      },
      {
        "command_type": "comment",
        "pipette": "left",
        "message": "\nSTEP - dry beads\n"
      },
      {
        "command_type": "delay",
        "pipette": "left",
        "minutes": "time_dry"
      },
      {
        "command_type": "comment",
        "pipette": "left",
        "message": "\nSTEP - elute and engage magnets\n"
      },
      {
        "command_type": "disengage_magnets",
        "module": "mag"
      },
      {
        "command_type": "transfer",
        "pipette": "right",
        "volume": 20,
        "source_labware": "",
        "source_well": "A1",
        "dest_labware": "",
        "dest_well": "A1",
        "new_tip": "always",
        "mix_after": [
          5,
          16
        ]
      },
      {
        "command_type": "delay",
        "pipette": "left",
        "minutes": 2
      },
      {
        "command_type": "engage_magnets",
        "module": "mag"
      },
      {
        "command_type": "delay",
        "pipette": "left",
        "minutes": "time_engage"
      },
      {
        "command_type": "comment",
        "pipette": "left",
        "message": "\nSTEP - recover eluate\n"
      },
      {
        "command_type": "transfer",
        "pipette": "left",
        "volume": 17,
        "source_labware": "",
        "source_well": "A1",
        "dest_labware": "",
        "dest_well": "A1",
        "new_tip": "always"
      },
      {
        "command_type": "transfer",
        "pipette": "left",
        "volume": 2,
        "source_labware": "",
        "source_well": "A1",
        "dest_labware": "",
        "dest_well": "A1",
        "new_tip": "always"
      },
      {
        "command_type": "comment",
        "pipette": "left",
        "message": "\nSTEP - qPCR mix to determine endpoint PCR cycles\n"
      },
      {
        "command_type": "transfer",
        "pipette": "left",
        "volume": "vol",
        "source_labware": "",
        "source_well": "A1",
        "dest_labware": "",
        "dest_well": "A1",
        "new_tip": "always"
      },
      {
        "command_type": "pause",
        "pipette": "left",
        "message": "format"
      },
      {
        "command_type": "comment",
        "pipette": "left",
        "message": "\nSTEP - assemble endpoint PCR mastermix\n"
      },
      {
        "command_type": "transfer",
        "pipette": "left",
        "volume": "vol",
        "source_labware": "",
        "source_well": "A1",
        "dest_labware": "",
        "dest_well": "A1",
        "new_tip": "always"
      },
      {
        "command_type": "comment",
        "pipette": "left",
        "message": "\nSTEP - add PCR mastermix\n"
      },
      {
        "command_type": "transfer",
        "pipette": "left",
        "volume": 18,
        "source_labware": "",
        "source_well": "A1",
        "dest_labware": "",
        "dest_well": "A1",
        "new_tip": "always"
      },
      {
        "command_type": "pause",
        "pipette": "left",
        "message": "Pausing for PCR. When finished, return plate to slot 5. Resume."
      },
      {
        "command_type": "comment",
        "pipette": "left",
        "message": "\nSTEP - transfer PCR reaction to mag plate\n"
      },
      {
        "command_type": "transfer",
        "pipette": "right",
        "volume": 35,
        "source_labware": "",
        "source_well": "A1",
        "dest_labware": "",
        "dest_well": "A1",
        "new_tip": "always"
      },
      {
        "command_type": "comment",
        "pipette": "left",
        "message": "\nSTEP - add beads\n"
      },
      {
        "command_type": "pick_up_tip",
        "pipette": "right"
      },
      {
        "command_type": "aspirate",
        "pipette": "right",
        "volume": "vol_premix"
      },
      {
        "command_type": "dispense",
        "pipette": "right",
        "volume": "vol_premix"
      },
      {
        "command_type": "aspirate",
        "pipette": "right",
        "volume": 31.5
      },
      {
        "command_type": "delay",
        "pipette": "left",
        "seconds": 1
      },
      {
        "command_type": "touch_tip",
        "pipette": "right"
      },
      {
        "command_type": "air_gap",
        "pipette": "right",
        "volume": 15
      },
      {
        "command_type": "dispense",
        "pipette": "right",
        "volume": 31.5
      },
      {
        "command_type": "mix",
        "pipette": "right",
        "repetitions": 5,
        "volume": 50
      },
      {
        "command_type": "blow_out",
        "pipette": "right"
      },
      {
        "command_type": "touch_tip",
        "pipette": "right"
      },
      {
        "command_type": "drop_tip",
        "pipette": "right"
      },
      {
        "command_type": "delay",
        "pipette": "left",
        "minutes": 5
      },
      {
        "command_type": "engage_magnets",
        "module": "mag"
      },
      {
        "command_type": "delay",
        "pipette": "left",
        "minutes": "time_engage"
      },
      {
        "command_type": "comment",
        "pipette": "left",
        "message": "\nSTEP - remove sup\n"
      },
      {
        "command_type": "pick_up_tip",
        "pipette": "right"
      },
      {
        "command_type": "aspirate",
        "pipette": "right",
        "volume": 70
      },
      {
        "command_type": "air_gap",
        "pipette": "right",
        "volume": 20
      },
      {
        "command_type": "drop_tip",
        "pipette": "right"
      },
      {
        "command_type": "comment",
        "pipette": "left",
        "message": "\nSTEP - elute, add ps, enage magnets\n"
      },
      {
        "command_type": "disengage_magnets",
        "module": "mag"
      },
      {
        "command_type": "transfer",
        "pipette": "right",
        "volume": 30,
        "source_labware": "",
        "source_well": "A1",
        "dest_labware": "",
        "dest_well": "A1",
        "new_tip": "always",
        "mix_after": [
          5,
          24
        ]
      },
      {
        "command_type": "delay",
        "pipette": "left",
        "minutes": 2
      },
      {
        "command_type": "transfer",
        "pipette": "right",
        "volume": 30,
        "source_labware": "",
        "source_well": "A1",
        "dest_labware": "",
        "dest_well": "A1",
        "new_tip": "always",
        "mix_after": [
          5,
          48
        ]
      },
      {
        "command_type": "delay",
        "pipette": "left",
        "minutes": 5
      },
      {
        "command_type": "engage_magnets",
        "module": "mag"
      },
      {
        "command_type": "delay",
        "pipette": "left",
        "minutes": "time_engage"
      },
      {
        "command_type": "comment",
        "pipette": "left",
        "message": "\nSTEP - remove sup\n"
      },
      {
        "command_type": "pick_up_tip",
        "pipette": "right"
      },
      {
        "command_type": "aspirate",
        "pipette": "right",
        "volume": 70
      },
      {
        "command_type": "air_gap",
        "pipette": "right",
        "volume": 20
      },
      {
        "command_type": "drop_tip",
        "pipette": "right"
      },
      {
        "command_type": "comment",
        "pipette": "left",
        "message": "\nSTEP - add 80 percent EtOH\n"
      },
      {
        "command_type": "pick_up_tip",
        "pipette": "right"
      },
      {
        "command_type": "aspirate",
        "pipette": "right",
        "volume": 120
      },
      {
        "command_type": "air_gap",
        "pipette": "right",
        "volume": 20
      },
      {
        "command_type": "dispense",
        "pipette": "right",
        "volume": 140
      },
      {
        "command_type": "delay",
        "pipette": "left",
        "seconds": 1
      },
      {
        "command_type": "blow_out",
        "pipette": "right"
      },
      {
        "command_type": "delay",
        "pipette": "left",
        "seconds": 30
      },
      {
        "command_type": "comment",
        "pipette": "left",
        "message": "\nSTEP - remove sup\n"
      },
      {
        "command_type": "air_gap",
        "pipette": "right",
        "volume": 20
      },
      {
        "command_type": "aspirate",
        "pipette": "right",
        "volume": 100
      },
      {
        "command_type": "aspirate",
        "pipette": "right",
        "volume": 60
      },
      {
        "command_type": "air_gap",
        "pipette": "right",
        "volume": 20
      },
      {
        "command_type": "drop_tip",
        "pipette": "right"
      },
      {
        "command_type": "dispense",
        "pipette": "right",
        "volume": 200
      },
      {
        "command_type": "delay",
        "pipette": "left",
        "seconds": 1
      },
      {
        "command_type": "blow_out",
        "pipette": "right"
      },
      {
        "command_type": "aspirate",
        "pipette": "right",
        "volume": 25
      },
      {
        "command_type": "drop_tip",
        "pipette": "right"
      },
      {
        "command_type": "comment",
        "pipette": "left",
        "message": "\nSTEP - dry beads\n"
      },
      {
        "command_type": "delay",
        "pipette": "left",
        "minutes": "time_dry"
      },
      {
        "command_type": "comment",
        "pipette": "left",
        "message": "\nSTEP - elute and engage magnets\n"
      },
      {
        "command_type": "disengage_magnets",
        "module": "mag"
      },
      {
        "command_type": "transfer",
        "pipette": "right",
        "volume": 20,
        "source_labware": "",
        "source_well": "A1",
        "dest_labware": "",
        "dest_well": "A1",
        "new_tip": "always",
        "mix_after": [
          5,
          16
        ]
      },
      {
        "command_type": "delay",
        "pipette": "left",
        "minutes": 2
      },
      {
        "command_type": "engage_magnets",
        "module": "mag"
      },
      {
        "command_type": "delay",
        "pipette": "left",
        "minutes": "time_engage"
      },
      {
        "command_type": "comment",
        "pipette": "left",
        "message": "\nSTEP - recover eluate\n"
      },
      {
        "command_type": "transfer",
        "pipette": "left",
        "volume": 17,
        "source_labware": "",
        "source_well": "A1",
        "dest_labware": "",
        "dest_well": "A1",
        "new_tip": "always"
      },
      {
        "command_type": "comment",
        "pipette": "left",
        "message": "\nProcess complete\n"
      }
    ]
  }
}