{
  "id": "ex_casual_db12c0b6",
  "intent": "Take samples from small 2mL tubes and pool them into larger 15mL tubes based on a spreadsheet that tells you which tubes go where and how much to transfer. The robot checks that you scanned the right tube racks and keeps track of which tips it's used so it doesn't waste them between runs.",
  "config": {
    "labware": {
      "tuberack": {
        "load_name": "eurofins_96x2ml_tuberack",
        "slot": "2"
      },
      "rack15": {
        "load_name": "opentrons_15_tuberack_falcon_15ml_conical",
        "slot": "1"
      }
    },
    "pipettes": {
      "p300_mount": {
        "model": "p300_single_gen2",
        "tipracks": []
      }
    }
  },
  "style": "casual",
  "source_file": "pooling.ot2.apiv2.py",
  "output_schema": {
    "protocol_name": "Pooling - 2ml Tuberack to 15ml Tuberack",
    "author": "Nick <protocols@opentrons.com>",
    "labware": [
      {
        "slot": "2",
        "load_name": "eurofins_96x2ml_tuberack",
        "label": "tuberack"
      },
      {
        "slot": "1",
        "load_name": "opentrons_15_tuberack_falcon_15ml_conical",
        "label": "rack15"
      }
    ],
    "pipettes": [
      {
        "mount": "p300_mount",
        "model": "p300_single_gen2",
        "tipracks": []
      }
    ],
    "modules": [],
    "commands": [
      {
        "command_type": "pause",
        "pipette": "left",
        "message": null
      },
      {
        "command_type": "pick_up_tip",
        "pipette": "left"
      },
      {
        "command_type": "pick_up_tip",
        "pipette": "left"
      },
      {
        "command_type": "drop_tip",
        "pipette": "p300_mount"
      },
      {
        "command_type": "air_gap",
        "pipette": "p300_mount",
        "volume": 20
      },
      {
        "command_type": "aspirate",
        "pipette": "p300_mount",
        "volume": "vol"
      },
      {
        "command_type": "dispense",
        "pipette": "p300_mount",
        "volume": null
      },
      {
        "command_type": "delay",
        "pipette": "left",
        "seconds": 1
      },
      {
        "command_type": "blow_out",
        "pipette": "p300_mount"
      },
      {
        "command_type": "drop_tip",
        "pipette": "p300_mount"
      }
    ]
  }
}