{
  "id": "ex_technical_da1293f1",
  "intent": "Execute a Promega ADP-Glo kinase assay protocol by sequentially dispensing four reagents (liquids A-D) from 1.5mL Eppendorf tubes to specified sample wells in a 384-well Greiner plate using a P20 single-channel pipette. Transfer each liquid with touch tip, followed by centrifugation and timed incubations: liquid A with centrifuge mixing, liquid B with 60-minute incubation, liquid C with 40-minute incubation, and liquid D with 30-minute incubation.",
  "config": {
    "labware": {
      "plate": {
        "load_name": "greiner_384_wellplate_130ul",
        "slot": "1"
      },
      "tiprack": {
        "load_name": "opentrons_96_tiprack_20ul",
        "slot": "2"
      },
      "tuberack": {
        "load_name": "opentrons_24_tuberack_eppendorf_1.5ml_safelock_snapcap",
        "slot": "4"
      }
    },
    "pipettes": {
      "left": {
        "model": "p20_single_gen2",
        "tipracks": [
          "tiprack"
        ]
      }
    }
  },
  "style": "technical",
  "source_file": "58d57d.ot2.apiv2.py",
  "output_schema": {
    "protocol_name": "Promega ADP-Glo Kinase Assay",
    "author": "Sakib <sakib.hossain@opentrons.com>",
    "labware": [
      {
        "slot": "1",
        "load_name": "greiner_384_wellplate_130ul",
        "label": "plate"
      },
      {
        "slot": "2",
        "load_name": "opentrons_96_tiprack_20ul",
        "label": "tiprack"
      },
      {
        "slot": "4",
        "load_name": "opentrons_24_tuberack_eppendorf_1.5ml_safelock_snapcap",
        "label": "tuberack"
      }
    ],
    "pipettes": [
      {
        "mount": "left",
        "model": "p20_single_gen2",
        "tipracks": [
          "tiprack"
        ]
      }
    ],
    "modules": [],
    "commands": [
      {
        "command_type": "transfer",
        "pipette": "left",
        "volume": "liquid_A_vol",
        "source_labware": "",
        "source_well": "A1",
        "dest_labware": "",
        "dest_well": "A1",
        "new_tip": "always"
      },
      {
        "command_type": "pause",
        "pipette": "left",
        "message": "Centrifuge Plate to Mix Liquid A"
      },
      {
        "command_type": "transfer",
        "pipette": "left",
        "volume": "liquid_B_vol",
        "source_labware": "",
        "source_well": "A1",
        "dest_labware": "",
        "dest_well": "A1",
        "new_tip": "always"
      },
      {
        "command_type": "pause",
        "pipette": "left",
        "message": "Centrifuge Plate and Incubate for 60 minutes"
      },
      {
        "command_type": "transfer",
        "pipette": "left",
        "volume": "liquid_C_vol",
        "source_labware": "",
        "source_well": "A1",
        "dest_labware": "",
        "dest_well": "A1",
        "new_tip": "always"
      },
      {
        "command_type": "pause",
        "pipette": "left",
        "message": "Incubate for 40 minutes"
      },
      {
        "command_type": "transfer",
        "pipette": "left",
        "volume": "liquid_D_vol",
        "source_labware": "",
        "source_well": "A1",
        "dest_labware": "",
        "dest_well": "A1",
        "new_tip": "always"
      },
      {
        "command_type": "pause",
        "pipette": "left",
        "message": "Incubate for 30 minutes"
      }
    ]
  }
}