{
  "id": "ex_technical_5979b61f",
  "intent": "Execute PCR sample pooling protocol transferring samples from a 384-well plate to a 96-well PCR plate. Using a P20 multichannel pipette, aspirate 3\u00b5L from 12 source wells in the 384-well plate (arranged in specific row/column patterns starting from rows A-B and columns 1-2) with 3\u00b5L air gaps between aspirations, then dispense the consolidated 18\u00b5L volume into designated pooling wells (A1, A3, A5, A7) of the 96-well plate. Repeat for 4 different pooling groups.",
  "config": {
    "labware": {
      "pcr_plate_384": {
        "load_name": "custom_384_wellplate_50ul",
        "slot": "8"
      },
      "pool_plate": {
        "load_name": "nest_96_wellplate_100ul_pcr_full_skirt",
        "slot": "5"
      }
    },
    "pipettes": {
      "p20_mount": {
        "model": "p20_multi_gen2",
        "tipracks": []
      }
    }
  },
  "style": "technical",
  "source_file": "08fd01-pt3.ot2.apiv2.py",
  "output_schema": {
    "protocol_name": "PCR Prep and Pooling with 384 Plates",
    "author": "Rami Farawi <rami.farawi@opentrons.com>",
    "labware": [
      {
        "slot": "8",
        "load_name": "custom_384_wellplate_50ul",
        "label": "pcr_plate_384"
      },
      {
        "slot": "5",
        "load_name": "nest_96_wellplate_100ul_pcr_full_skirt",
        "label": "pool_plate"
      }
    ],
    "pipettes": [
      {
        "mount": "p20_mount",
        "model": "p20_multi_gen2",
        "tipracks": []
      }
    ],
    "modules": [],
    "commands": [
      {
        "command_type": "pick_up_tip",
        "pipette": "p20_mount"
      },
      {
        "command_type": "aspirate",
        "pipette": "p20_mount",
        "volume": 3
      },
      {
        "command_type": "air_gap",
        "pipette": "p20_mount",
        "volume": "airgap"
      },
      {
        "command_type": "dispense",
        "pipette": "p20_mount",
        "volume": null
      },
      {
        "command_type": "drop_tip",
        "pipette": "p20_mount"
      }
    ]
  }
}