{
  "id": "ex_technical_e1b01851",
  "source_file": "78d33c-part-5.ot2.apiv2.py",
  "intent_precise": "78d33c-part-5.ot2.apiv2: Using Reagents (labware, slot 2), sampleplate (labware, slot Sample Plate at 4 Degrees). With temperature module, magnetic module. (1) Pause: format (2) Set temperature to 4\u00b0C. (3) Disengage magnets to release beads. (4) Transfer 5\u00b5L from postindexcleanup_enz_mx 0 to column 0. (5) Transfer 20\u00b5L from column 0 to destination. (6) Pause: Post-indexing purification protocol complete.\n     Proceed to off deck cycler steps\n     and library purification protocol",
  "intent_concise": "Perform magnetic bead separation, temperature control (4\u00b0C). (volumes 5\u00b5L-20\u00b5L)",
  "intent": "For this post-indexing cleanup step, start by setting your temperature module to 4\u00b0C and make sure to disengage the magnets to release the beads from the magnetic module. Transfer 5\u00b5L from the postindexcleanup_enz_mx at position 0 to column 0 of your sample plate, then transfer 20\u00b5L from that same column 0 to your destination wells. Once you've completed these transfers, you can proceed with the off-deck cycler steps followed by the library purification protocol.",
  "style": "scientist",
  "output_schema": {
    "protocol_name": "78d33c-part-5.ot2.apiv2",
    "author": "Steve Plonk <protocols@opentrons.com>",
    "labware": [
      {
        "slot": "2",
        "load_name": "opentrons_96_aluminumblock_generic_pcr_strip_200ul",
        "label": "Reagents"
      },
      {
        "slot": "Sample Plate at 4 Degrees",
        "load_name": "eppendorftwin.tec96_96_aluminumblock_200ul",
        "label": "sampleplate"
      }
    ],
    "pipettes": [
      {
        "mount": "left",
        "model": "p20_multi_gen2",
        "tipracks": []
      }
    ],
    "modules": [
      {
        "module_type": "temperature",
        "slot": "3",
        "label": "temp"
      },
      {
        "module_type": "magnetic",
        "slot": "1",
        "label": "mag"
      }
    ],
    "commands": [
      {
        "command_type": "pick_up_tip",
        "pipette": "left"
      },
      {
        "command_type": "pause",
        "pipette": "left",
        "message": "format"
      },
      {
        "command_type": "pick_up_tip",
        "pipette": "left"
      },
      {
        "command_type": "set_temperature",
        "module": "temp",
        "celsius": 4
      },
      {
        "command_type": "disengage_magnets",
        "module": "mag"
      },
      {
        "command_type": "comment",
        "pipette": "left",
        "message": "STEP - Post-Indexing Cleanup Enzyme Mixture"
      },
      {
        "command_type": "transfer",
        "pipette": "left",
        "volume": 5,
        "source_labware": "postindexcleanup_enz_mx",
        "source_well": "0",
        "dest_labware": "column",
        "dest_well": "0",
        "new_tip": "never"
      },
      {
        "command_type": "aspirate",
        "pipette": "left",
        "volume": 20,
        "labware": "column",
        "well": "0"
      },
      {
        "command_type": "dispense",
        "pipette": "left",
        "volume": 20
      },
      {
        "command_type": "drop_tip",
        "pipette": "left"
      },
      {
        "command_type": "pause",
        "pipette": "left",
        "message": "Post-indexing purification protocol complete.\n     Proceed to off deck cycler steps\n     and library purification protocol"
      }
    ]
  },
  "config": {
    "labware": {
      "Reagents": {
        "load_name": "opentrons_96_aluminumblock_generic_pcr_strip_200ul",
        "slot": "2"
      },
      "sampleplate": {
        "load_name": "eppendorftwin.tec96_96_aluminumblock_200ul",
        "slot": "Sample Plate at 4 Degrees"
      }
    },
    "pipettes": {
      "left": {
        "model": "p20_multi_gen2",
        "tipracks": []
      }
    },
    "modules": {
      "temp": {
        "module_type": "temperature",
        "slot": "3"
      },
      "mag": {
        "module_type": "magnetic",
        "slot": "1"
      }
    }
  }
}