{
  "id": "ex_technical_228bd0fb",
  "source_file": "0961d2-part1.ot2.apiv2.py",
  "intent_precise": "plexWell LP384 Part 1: Using res (reservoir, slot 9). (1) Transfer 6\u00b5L from source A1 to destination A1. (2) Mix 5 times at 6\u00b5L. (3) Transfer 5\u00b5L from source A1 to destination A1. (4) Mix 10 times at 5\u00b5L.",
  "intent_concise": "Execute 11-step liquid handling protocol. (volumes 5\u00b5L-6\u00b5L)",
  "intent": "For the plexWell LP384 Part 1 protocol, you'll be working with the reservoir in slot 9. Start by transferring 6\u00b5L from source well A1 to destination well A1, then mix it 5 times using the 6\u00b5L volume. Next, transfer 5\u00b5L from the same source A1 to destination A1, and finish by mixing 10 times at the 5\u00b5L volume.",
  "style": "scientist",
  "output_schema": {
    "protocol_name": "plexWell LP384 Part 1",
    "author": "Chaz <protocols@opentrons.com>",
    "labware": [
      {
        "slot": "9",
        "load_name": "nest_12_reservoir_15ml",
        "label": "res"
      }
    ],
    "pipettes": [
      {
        "mount": "p10_mnt",
        "model": "p10_multi",
        "tipracks": []
      }
    ],
    "modules": [],
    "commands": [
      {
        "command_type": "pick_up_tip",
        "pipette": "p10_mnt"
      },
      {
        "command_type": "transfer",
        "pipette": "p10_mnt",
        "volume": 6,
        "source_labware": "",
        "source_well": "A1",
        "dest_labware": "",
        "dest_well": "A1",
        "new_tip": "never"
      },
      {
        "command_type": "mix",
        "pipette": "p10_mnt",
        "repetitions": 5,
        "volume": 6
      },
      {
        "command_type": "blow_out",
        "pipette": "p10_mnt"
      },
      {
        "command_type": "drop_tip",
        "pipette": "p10_mnt"
      },
      {
        "command_type": "pick_up_tip",
        "pipette": "p10_mnt"
      },
      {
        "command_type": "transfer",
        "pipette": "p10_mnt",
        "volume": 5,
        "source_labware": "",
        "source_well": "A1",
        "dest_labware": "",
        "dest_well": "A1",
        "new_tip": "never"
      },
      {
        "command_type": "mix",
        "pipette": "p10_mnt",
        "repetitions": 10,
        "volume": 5
      },
      {
        "command_type": "blow_out",
        "pipette": "p10_mnt"
      },
      {
        "command_type": "drop_tip",
        "pipette": "p10_mnt"
      },
      {
        "command_type": "comment",
        "pipette": "left",
        "message": "Part 1 now complete. Seal plates in slots 3 and 6,     pulse-spin, and run on thermal cycler."
      }
    ]
  },
  "config": {
    "labware": {
      "res": {
        "load_name": "nest_12_reservoir_15ml",
        "slot": "9"
      }
    },
    "pipettes": {
      "left": {
        "model": "p10_multi",
        "tipracks": []
      }
    }
  }
}